PhonTactProb/PhonTactProb.py
PhonTactProb/__init__.py
PhonTactProb/data/dictionary.txt
phontactprob-0.1.0.dist-info/licenses/LICENSE
phontactprob-0.1.0.dist-info/METADATA
phontactprob-0.1.0.dist-info/WHEEL
phontactprob-0.1.0.dist-info/top_level.txt
phontactprob-0.1.0.dist-info/RECORD
