Metadata-Version: 2.4
Name: PhonTactProb
Version: 0.1.0
Summary: A package to compute phonotactic probabilities using NLTK and IPA.
Author-email: Timo <tiyliu@ucdavis.edu>
License: MIT License
Project-URL: Homepage, https://github.com/timo-liu/PhonTactProb
Project-URL: Issues, https://github.com/timo-liu/PhonTactProb/issues
Requires-Python: >=3.8
License-File: LICENSE
Requires-Dist: nltk>=3.8.1
Dynamic: license-file
